{"name":"JavaWeb","slug":"JavaWeb","count":1,"postlist":[{"title":"junit、反射","uid":"7ee1f34768cc2e04e0232a752344cda0","slug":"junit、注解、反射","date":"2022-06-19T12:28:37.000Z","updated":"2022-06-20T00:48:00.769Z","comments":true,"path":"api/articles/junit、注解、反射.json","keywords":null,"cover":"https://ts1.cn.mm.bing.net/th/id/R-C.e953db8584262c6d275ebb1f463e2664?rik=310ufjsemnBz1Q&riu=http%3a%2f%2fup.deskcity.org%2fpic_source%2fe9%2f53%2fdb%2fe953db8584262c6d275ebb1f463e2664.jpg&ehk=f4G2vlmXEKODWmUbTuTJbYW%2bLjy81wyNtMx3vLsrh8o%3d&risl=&pid=ImgRaw&r=0","text":"# 1、junit 单元测试 # 1.1 测试分类： 黑盒测试：不用具体关注里面的代码内容，只要输入 input，经过代码的执行查看 output 是否达到预期，不需要写测试代码 白盒测试：也需要 input 和 output，但是输入了之后代码的执行，代码的逻辑、算法、严谨度、...","link":"","photos":[],"count_time":{"symbolsCount":"13k","symbolsTime":"12 mins."},"categories":[{"name":"JavaWeb","slug":"JavaWeb","count":1,"path":"api/categories/JavaWeb.json"}],"tags":[{"name":"JavaWeb","slug":"JavaWeb","count":1,"path":"api/tags/JavaWeb.json"}],"author":{"name":"cCor4ng3","slug":"blog-author","avatar":"http://wuriteup.oss-cn-qingdao.aliyuncs.com/img/53BC80F5D1388E1A7955F40466B7F050.jpg","link":"/","description":"Fight 为 · Live","socials":{"github":"","twitter":"","stackoverflow":"","wechat":"","qq":"","weibo":"","zhihu":"","csdn":"","juejin":"","customs":{}}},"feature":true}]}